Metadata-Version: 2.1
Name: cognitive-services
Version: 0.0.1
Summary: A package that wraps many cognitive services packages
Home-page: https://github.com/franklin.lindemberg/cognitive-services
Author: Franklin Lindemberg Guimaraes
Author-email: franklin.lindemberg@seedin.ai
License: UNKNOWN
Platform: UNKNOWN
Classifier: Programming Language :: Python :: 3
Classifier: License :: OSI Approved :: MIT License
Classifier: Operating System :: OS Independent
